{"version":1,"resource":"file:///Users/marcellemendes/Documents/code/my-app/src/App.js","entries":[{"id":"sPeT.js","timestamp":1678374531595},{"id":"q1b6.js","timestamp":1678378542874},{"id":"xOro.js","timestamp":1678378556113},{"id":"MTWh.js","timestamp":1678378678955},{"id":"6W5p.js","timestamp":1678378693076},{"id":"66Tr.js","timestamp":1678378762868},{"id":"xKNW.jsx","source":"renamed.source","timestamp":1678378876374},{"id":"7raK.js","source":"renamed.source","timestamp":1678378904569},{"id":"xFAO.js","timestamp":1678378956489},{"id":"N9hr.js","timestamp":1678379152365},{"id":"2FdV.js","timestamp":1678388709147},{"id":"th5g.js","timestamp":1678388774718},{"id":"i2ak.js","timestamp":1678388890991},{"id":"WPTM.js","timestamp":1678389140191},{"id":"kkAH.js","timestamp":1678389517381},{"id":"pkCr.js","timestamp":1678389527720}]}